munchie/__init__.py
munchie/__main__.py
munchie/constants.py
munchie/filenom/__init__.py
munchie/filenom/file_nom.py
munchie/filenom/utils.py
munchie-0.1.4.dist-info/WHEEL
munchie-0.1.4.dist-info/METADATA
munchie-0.1.4.dist-info/RECORD
